inte_labs/__init__.py
inte_labs/admin.py
inte_labs/aliquot_types.py
inte_labs/apps.py
inte_labs/lab_profiles.py
inte_labs/labs.py
inte_labs/list_data.py
inte_labs/panels.py
inte_labs/processing_profiles.py
inte_labs/reportables.py
inte_labs/tests/__init__.py
inte_labs/tests/test_labs.py
inte_labs/tests/test_reportables.py
inte_labs/tests/urls.py
inte_labs-0.1.2.dist-info/LICENSE
inte_labs-0.1.2.dist-info/METADATA
inte_labs-0.1.2.dist-info/WHEEL
inte_labs-0.1.2.dist-info/top_level.txt
inte_labs-0.1.2.dist-info/RECORD
